mcp_input_analyzer/__init__.py
mcp_input_analyzer/main.py
mcp_input_analyzer-0.1.0.dist-info/METADATA
mcp_input_analyzer-0.1.0.dist-info/WHEEL
mcp_input_analyzer-0.1.0.dist-info/top_level.txt
mcp_input_analyzer-0.1.0.dist-info/RECORD
